soiltex/__init__.py
soiltex/conversion.py
soiltex/version.py
soiltex-1.0.0.dist-info/AUTHORS.rst
soiltex-1.0.0.dist-info/LICENSE
soiltex-1.0.0.dist-info/METADATA
soiltex-1.0.0.dist-info/WHEEL
soiltex-1.0.0.dist-info/top_level.txt
soiltex-1.0.0.dist-info/RECORD
