Metadata-Version: 2.1
Name: soiltex
Version: 1.0.0
Summary: Soil texture definition
Home-page: https://gitlab.com/revesansparole/soiltex
Author: revesansparole
Author-email: revesansparole@gmail.com
License: cc_by_nc
Platform: UNKNOWN
Classifier: Development Status :: 2 - Pre-Alpha
Classifier: Intended Audience :: Developers
Classifier: License :: OSI Approved :: BSD License
Classifier: Natural Language :: English
Classifier: Programming Language :: Python
Classifier: Programming Language :: Python :: 3
Classifier: Programming Language :: Python :: 3 :: Only
Classifier: Programming Language :: Python :: 3.9
